{"profile":{"name":"Mohamed Ahmed Hassan Elsaqa","mobile":"201014027537","email":"mohamedahmedhassanelsaqa@italianista.com","password":201014027537,"group":"Catania","courseType":"Regular Course","courseStatus":"Offline"},"support":{"instructorName":"Mahmoud Tahoun","instructorMobile":201284508183},"schedule":"الأحد الساعة 8:00 مساءً و الأربعاء الساعة 8:00 مساءً","stats":{"started":"04/08/2026","totalIn":1,"totalNs":0,"totalPaid":1000,"totalOvd":0},"progress":{"percent":0,"currentTopic":"Not Started","nextTopic":"1 - Phase 1 / Livello A1 / La Pronunucia (النطق)","currentSession":0,"totalSessions":80},"lastUpdated":"4/8/2026, 9:50:03 PM"}